cdk_lib/__init__.py
cdk_lib/s3.py
cdk_lib-0.1.0.dist-info/METADATA
cdk_lib-0.1.0.dist-info/WHEEL
cdk_lib-0.1.0.dist-info/RECORD
