Metadata-Version: 2.1
Name: cdk-lib
Version: 0.1.0
Summary: 
Author: Keith Lagrange
Author-email: punolagrange@gmail.com
Requires-Python: >=3.12,<4.0
Classifier: Programming Language :: Python :: 3
Classifier: Programming Language :: Python :: 3.12
Requires-Dist: aws-cdk-lib (>=2.153.0,<3.0.0)
Requires-Dist: pytest (>=8.3.2,<9.0.0)
